README.rst
setup.py
BelgradeRealEstateAppAdventisrealestate.egg-info/PKG-INFO
BelgradeRealEstateAppAdventisrealestate.egg-info/SOURCES.txt
BelgradeRealEstateAppAdventisrealestate.egg-info/dependency_links.txt
BelgradeRealEstateAppAdventisrealestate.egg-info/entry_points.txt
BelgradeRealEstateAppAdventisrealestate.egg-info/requires.txt
BelgradeRealEstateAppAdventisrealestate.egg-info/top_level.txt
RealEstateApp/__init__.py
RealEstateApp/real_estate_app.py