Metadata-Version: 2.1
Name: BelgradeRealEstateAppAdventisrealestate
Version: 0.8
Summary: Script that runs a web scraper in a background and gets all available real estates in Belgrade, and filters them by given parameters.
Home-page: https://github.com/urosjevremovic/Belgrade-real-estate-app-adventisrealestate
Author: Uros Jevremovic
Author-email: jevremovic.uros91@gmail.com
License: MIT
Platform: UNKNOWN
